{
    "spanId": "a39de5c02c3bb8ff",
    "traceId": "939f2e2d83a1c32f40f7a86f4e5cacef",
    "parent": "File_Ops_Copy_Test",
    "all-info": "span(name: fileOperations, spanId: a39de5c02c3bb8ff, parentSpanId: 35737607f38c09af, traceId: 939f2e2d83a1c32f40f7a86f4e5cacef, attr: ci.pipeline.run.user:SYSTEM;harness-attribute:{\r\n  \"delegate\" : {\r\n    \"symbol\" : \"fileOperations\",\r\n    \"klass\" : null,\r\n    \"arguments\" : {\r\n      \"<anonymous>\" : [ {\r\n        \"symbol\" : \"fileCopyOperation\",\r\n        \"klass\" : null,\r\n        \"arguments\" : {\r\n          \"includes\" : \"src/*.txt\",\r\n          \"excludes\" : \"\",\r\n          \"targetLocation\" : \"dest/\",\r\n          \"flattenFiles\" : false,\r\n          \"renameFiles\" : false,\r\n          \"sourceCaptureExpression\" : \"\",\r\n          \"targetNameExpression\" : \"\",\r\n          \"useDefaultExcludes\" : true\r\n        },\r\n        \"model\" : null,\r\n        \"interpolatedStrings\" : [ ]\r\n      } ]\r\n    },\r\n    \"model\" : null\r\n  }\r\n};harness-attribute-extra-pip: io.jenkins.plugins.opentelemetry.MigrateHarnessUrlChildAction@30d15708:io.jenkins.plugins.opentelemetry.MigrateHarnessUrlChildAction@30d15708;harness-attribute-extra-pip: org.jenkinsci.plugins.workflow.actions.TimingAction@26e009c8:org.jenkinsci.plugins.workflow.actions.TimingAction@26e009c8;harness-others:-delegate-field org.jenkinsci.plugins.workflow.steps.CoreStep delegate-org.jenkinsci.plugins.workflow.steps.CoreStep.delegate-interface jenkins.tasks.SimpleBuildStep;jenkins.pipeline.step.id:27;jenkins.pipeline.step.name:File Operations;jenkins.pipeline.step.plugin.name:file-operations;jenkins.pipeline.step.plugin.version:266.v9d4e1eb_235b_a_;jenkins.pipeline.step.type:fileOperations;)",
    "name": "File_Ops_Copy_Test #2",
    "attributesMap": {
        "harness-attribute-extra-pip: io.jenkins.plugins.opentelemetry.MigrateHarnessUrlChildAction@30d15708": "io.jenkins.plugins.opentelemetry.MigrateHarnessUrlChildAction@30d15708",
        "harness-others": "-delegate-field org.jenkinsci.plugins.workflow.steps.CoreStep delegate-org.jenkinsci.plugins.workflow.steps.CoreStep.delegate-interface jenkins.tasks.SimpleBuildStep",
        "jenkins.pipeline.step.name": "File Operations",
        "ci.pipeline.run.user": "SYSTEM",
        "jenkins.pipeline.step.id": "27",
        "jenkins.pipeline.step.type": "fileOperations",
        "harness-attribute": "{\r\n  \"delegate\" : {\r\n    \"symbol\" : \"fileOperations\",\r\n    \"klass\" : null,\r\n    \"arguments\" : {\r\n      \"<anonymous>\" : [ {\r\n        \"symbol\" : \"fileCopyOperation\",\r\n        \"klass\" : null,\r\n        \"arguments\" : {\r\n          \"includes\" : \"src/*.txt\",\r\n          \"excludes\" : \"\",\r\n          \"targetLocation\" : \"dest/\",\r\n          \"flattenFiles\" : false,\r\n          \"renameFiles\" : false,\r\n          \"sourceCaptureExpression\" : \"\",\r\n          \"targetNameExpression\" : \"\",\r\n          \"useDefaultExcludes\" : true\r\n        },\r\n        \"model\" : null,\r\n        \"interpolatedStrings\" : [ ]\r\n      } ]\r\n    },\r\n    \"model\" : null\r\n  }\r\n}",
        "jenkins.pipeline.step.plugin.name": "file-operations",
        "jenkins.pipeline.step.plugin.version": "266.v9d4e1eb_235b_a_",
        "harness-attribute-extra-pip: org.jenkinsci.plugins.workflow.actions.TimingAction@26e009c8": "org.jenkinsci.plugins.workflow.actions.TimingAction@26e009c8"
    },
    "type": "Run Phase Span",
    "parentSpanId": "35737607f38c09af",
    "parameterMap": {
        "delegate": {
            "symbol": "fileOperations",
            "klass": null,
            "arguments": {
                "<anonymous>": [
                    {
                        "symbol": "fileCopyOperation",
                        "klass": null,
                        "interpolatedStrings": [],
                        "arguments": {
                            "excludes": "",
                            "targetNameExpression": "",
                            "includes": "src/*.txt",
                            "flattenFiles": false,
                            "targetLocation": "dest/",
                            "renameFiles": false,
                            "sourceCaptureExpression": "",
                            "useDefaultExcludes": true
                        },
                        "model": null
                    }
                ]
            },
            "model": null
        }
    },
    "spanName": "fileOperations"
}